ClearData/Interfaces.py
ClearData/PostgreSQLClearData.py
ClearData/SQLServerClearData.py
ClearData/Statics.py
ClearData/TextClearData.py
ClearData/__init__.py
cleardata-2.0.7.dist-info/METADATA
cleardata-2.0.7.dist-info/WHEEL
cleardata-2.0.7.dist-info/licenses/LICENSE
cleardata-2.0.7.dist-info/RECORD
