Metadata-Version: 2.4
Name: ClearData
Version: 2.0.7
Summary: Utility library for accessing Data providers in a uniform way.
Project-URL: Homepage, https://github.com/bradleydonmorris/ClearData
Project-URL: Issues, https://github.com/bradleydonmorris/ClearData/issues
Author-email: Bradley Morris <bradleydonmorris@hotmail.com>
License-File: LICENSE
Classifier: License :: OSI Approved :: MIT License
Classifier: Operating System :: OS Independent
Classifier: Programming Language :: Python :: 3
Requires-Python: >=3.11
